AUTHORS.md
CHANGELOG.md
LICENSE
MANIFEST.in
README.md
setup.py
.github/CONTRIBUTING.md
schemaorg/__init__.py
schemaorg/defaults.py
schemaorg/utils.py
schemaorg/version.py
schemaorg.egg-info/PKG-INFO
schemaorg.egg-info/SOURCES.txt
schemaorg.egg-info/dependency_links.txt
schemaorg.egg-info/not-zip-safe
schemaorg.egg-info/requires.txt
schemaorg.egg-info/top_level.txt
schemaorg/data/__init__.py
schemaorg/data/ext/12.0/attic/attic.ttl
schemaorg/data/ext/12.0/auto/auto.ttl
schemaorg/data/ext/12.0/bib/bsdo-1.0.ttl
schemaorg/data/ext/12.0/bib/bsdo-atlas-examples.txt
schemaorg/data/ext/12.0/bib/bsdo-audiobook-examples.txt
schemaorg/data/ext/12.0/bib/bsdo-chapter-examples.txt
schemaorg/data/ext/12.0/bib/bsdo-collection-examples.txt
schemaorg/data/ext/12.0/bib/bsdo-newspaper-examples.txt
schemaorg/data/ext/12.0/bib/bsdo-thesis-examples.txt
schemaorg/data/ext/12.0/bib/bsdo-translation-examples.txt
schemaorg/data/ext/12.0/bib/comics-examples.txt
schemaorg/data/ext/12.0/health-lifesci/MedicalScholarlyArticle-examples.txt
schemaorg/data/ext/12.0/health-lifesci/drug-example.txt
schemaorg/data/ext/12.0/health-lifesci/med-health-core.ttl
schemaorg/data/ext/12.0/health-lifesci/medicalCondition-examples.txt
schemaorg/data/ext/12.0/health-lifesci/medicalGuideline-examples.txt
schemaorg/data/ext/12.0/health-lifesci/medicalWebpage-examples.txt
schemaorg/data/ext/12.0/health-lifesci/physical-activity-and-exercise.ttl
schemaorg/data/ext/12.0/meta/meta.jsonld.someday.txt
schemaorg/data/ext/12.0/meta/meta.ttl
schemaorg/data/ext/12.0/pending/issue-1045-examples.txt
schemaorg/data/ext/12.0/pending/issue-1045.ttl
schemaorg/data/ext/12.0/pending/issue-1050-examples.txt
schemaorg/data/ext/12.0/pending/issue-1050.ttl
schemaorg/data/ext/12.0/pending/issue-1062-examples.txt
schemaorg/data/ext/12.0/pending/issue-1062.ttl
schemaorg/data/ext/12.0/pending/issue-1083.ttl
schemaorg/data/ext/12.0/pending/issue-1156-examples.txt
schemaorg/data/ext/12.0/pending/issue-1156.ttl
schemaorg/data/ext/12.0/pending/issue-1244.ttl
schemaorg/data/ext/12.0/pending/issue-1253-examples.txt
schemaorg/data/ext/12.0/pending/issue-1253.ttl
schemaorg/data/ext/12.0/pending/issue-1375.ttl
