Metadata-Version: 2.1
Name: schemaorg
Version: 0.1.0
Summary: Python functions for applied use of schema.org
Home-page: https://github.com/openschemas/schemaorg
Author: Vanessa Sochat
Author-email: vsoch@users.noreply.github.com
Maintainer: Vanessa Sochat
Maintainer-email: vsoch@users.noreply.github.com
License: LICENSE
Keywords: openschemas,schema.org
Platform: UNKNOWN
Classifier: Intended Audience :: Science/Research
Classifier: Intended Audience :: Developers
Classifier: License :: OSI Approved :: GNU Affero General Public License v3 or later (AGPLv3+)
Classifier: Programming Language :: C
Classifier: Programming Language :: Python
Classifier: Topic :: Software Development
Classifier: Topic :: Scientific/Engineering
Classifier: Operating System :: Unix
Classifier: Programming Language :: Python :: 3
